Workbook

Sheet Produits
A1: 📦 PRODUITS (mobile) — Tu peux changer l'ID affiché sans casser le journal (PID interne immuable).
A2: Saisie (vert) : ID affiché, Nom, Catégorie, Unités/lot (référence). Les colonnes bleu clair sont calculées depuis le Journal (actif uniquement).
A3: PID (caché) | B3: ID produit (modifiable) | C3: Nom produit | D3: Catégorie | E3: Unités par lot (réf) | F3: Stock unités | G3: Stock lots (info) | H3: Reste unités | I3: Coût moyen achat (€) | J3: Note
A4: P69BCEF762C | B4: CP22X3 | C4: Contreplaqué 2mm 200x300 | D4: Bois | E4: 1 | F4: =IFERROR(SUMIFS(Journal!$K:$K,Journal!$B:$B,TRUE,Journal!$E:$E,A4),0) | G4: =IFERROR(INT(F4/E4),0) | H4: =IFERROR(MOD(F4,E4),0) | I4: =IFERROR(SUMIFS(Journal!$N:$N,Journal!$B:$B,TRUE,Journal!$D:$D,"ACHAT",Journal!$E:$E,A4)/SUMIFS(Journal!$K:$K,Journal!$B:$B,TRUE,Journal!$D:$D,"ACHAT",Journal!$E:$E,A4),"")
A5: P8B70051EAB | B5: CP23X3 | C5: Contreplaqué 2mm 300x300 | D5: Bois | E5: 1 | F5: =IFERROR(SUMIFS(Journal!$K:$K,Journal!$B:$B,TRUE,Journal!$E:$E,A5),0) | G5: =IFERROR(INT(F5/E5),0) | H5: =IFERROR(MOD(F5,E5),0) | I5: =IFERROR(SUMIFS(Journal!$N:$N,Journal!$B:$B,TRUE,Journal!$D:$D,"ACHAT",Journal!$E:$E,A5)/SUMIFS(Journal!$K:$K,Journal!$B:$B,TRUE,Journal!$D:$D,"ACHAT",Journal!$E:$E,A5),"")
A6: P6B0BD97B79 | B6: CP22X2 | C6: Contreplaqué 2mm 200x200 | D6: Bois | E6: 1 | F6: =IFERROR(SUMIFS(Journal!$K:$K,Journal!$B:$B,TRUE,Journal!$E:$E,A6),0) | G6: =IFERROR(INT(F6/E6),0) | H6: =IFERROR(MOD(F6,E6),0) | I6: =IFERROR(SUMIFS(Journal!$N:$N,Journal!$B:$B,TRUE,Journal!$D:$D,"ACHAT",Journal!$E:$E,A6)/SUMIFS(Journal!$K:$K,Journal!$B:$B,TRUE,Journal!$D:$D,"ACHAT",Journal!$E:$E,A6),"")
F7: =IFERROR(SUMIFS(Journal!$K:$K,Journal!$B:$B,TRUE,Journal!$E:$E,A7),0) | G7: =IFERROR(INT(F7/E7),0) | H7: =IFERROR(MOD(F7,E7),0) | I7: =IFERROR(SUMIFS(Journal!$N:$N,Journal!$B:$B,TRUE,Journal!$D:$D,"ACHAT",Journal!$E:$E,A7)/SUMIFS(Journal!$K:$K,Journal!$B:$B,TRUE,Journal!$D:$D,"ACHAT",Journal!$E:$E,A7),"")
F8: =IFERROR(SUMIFS(Journal!$K:$K,Journal!$B:$B,TRUE,Journal!$E:$E,A8),0) | G8: =IFERROR(INT(F8/E8),0) | H8: =IFERROR(MOD(F8,E8),0) | I8: =IFERROR(SUMIFS(Journal!$N:$N,Journal!$B:$B,TRUE,Journal!$D:$D,"ACHAT",Journal!$E:$E,A8)/SUMIFS(Journal!$K:$K,Journal!$B:$B,TRUE,Journal!$D:$D,"ACHAT",Journal!$E:$E,A8),"")
F9: =IFERROR(SUMIFS(Journal!$K:$K,Journal!$B:$B,TRUE,Journal!$E:$E,A9),0) | G9: =IFERROR(INT(F9/E9),0) | H9: =IFERROR(MOD(F9,E9),0) | I9: =IFERROR(SUMIFS(Journal!$N:$N,Journal!$B:$B,TRUE,Journal!$D:$D,"ACHAT",Journal!$E:$E,A9)/SUMIFS(Journal!$K:$K,Journal!$B:$B,TRUE,Journal!$D:$D,"ACHAT",Journal!$E:$E,A9),"")
F10: =IFERROR(SUMIFS(Journal!$K:$K,Journal!$B:$B,TRUE,Journal!$E:$E,A10),0) | G10: =IFERROR(INT(F10/E10),0) | H10: =IFERROR(MOD(F10,E10),0) | I10: =IFERROR(SUMIFS(Journal!$N:$N,Journal!$B:$B,TRUE,Journal!$D:$D,"ACHAT",Journal!$E:$E,A10)/SUMIFS(Journal!$K:$K,Journal!$B:$B,TRUE,Journal!$D:$D,"ACHAT",Journal!$E:$E,A10),"")
F11: =IFERROR(SUMIFS(Journal!$K:$K,Journal!$B:$B,TRUE,Journal!$E:$E,A11),0) | G11: =IFERROR(INT(F11/E11),0) | H11: =IFERROR(MOD(F11,E11),0) | I11: =IFERROR(SUMIFS(Journal!$N:$N,Journal!$B:$B,TRUE,Journal!$D:$D,"ACHAT",Journal!$E:$E,A11)/SUMIFS(Journal!$K:$K,Journal!$B:$B,TRUE,Journal!$D:$D,"ACHAT",Journal!$E:$E,A11),"")
F12: =IFERROR(SUMIFS(Journal!$K:$K,Journal!$B:$B,TRUE,Journal!$E:$E,A12),0) | G12: =IFERROR(INT(F12/E12),0) | H12: =IFERROR(MOD(F12,E12),0) | I12: =IFERROR(SUMIFS(Journal!$N:$N,Journal!$B:$B,TRUE,Journal!$D:$D,"ACHAT",Journal!$E:$E,A12)/SUMIFS(Journal!$K:$K,Journal!$B:$B,TRUE,Journal!$D:$D,"ACHAT",Journal!$E:$E,A12),"")
F13: =IFERROR(SUMIFS(Journal!$K:$K,Journal!$B:$B,TRUE,Journal!$E:$E,A13),0) | G13: =IFERROR(INT(F13/E13),0) | H13: =IFERROR(MOD(F13,E13),0) | I13: =IFERROR(SUMIFS(Journal!$N:$N,Journal!$B:$B,TRUE,Journal!$D:$D,"ACHAT",Journal!$E:$E,A13)/SUMIFS(Journal!$K:$K,Journal!$B:$B,TRUE,Journal!$D:$D,"ACHAT",Journal!$E:$E,A13),"")
F14: =IFERROR(SUMIFS(Journal!$K:$K,Journal!$B:$B,TRUE,Journal!$E:$E,A14),0) | G14: =IFERROR(INT(F14/E14),0) | H14: =IFERROR(MOD(F14,E14),0) | I14: =IFERROR(SUMIFS(Journal!$N:$N,Journal!$B:$B,TRUE,Journal!$D:$D,"ACHAT",Journal!$E:$E,A14)/SUMIFS(Journal!$K:$K,Journal!$B:$B,TRUE,Journal!$D:$D,"ACHAT",Journal!$E:$E,A14),"")
F15: =IFERROR(SUMIFS(Journal!$K:$K,Journal!$B:$B,TRUE,Journal!$E:$E,A15),0) | G15: =IFERROR(INT(F15/E15),0) | H15: =IFERROR(MOD(F15,E15),0) | I15: =IFERROR(SUMIFS(Journal!$N:$N,Journal!$B:$B,TRUE,Journal!$D:$D,"ACHAT",Journal!$E:$E,A15)/SUMIFS(Journal!$K:$K,Journal!$B:$B,TRUE,Journal!$D:$D,"ACHAT",Journal!$E:$E,A15),"")
F16: =IFERROR(SUMIFS(Journal!$K:$K,Journal!$B:$B,TRUE,Journal!$E:$E,A16),0) | G16: =IFERROR(INT(F16/E16),0) | H16: =IFERROR(MOD(F16,E16),0) | I16: =IFERROR(SUMIFS(Journal!$N:$N,Journal!$B:$B,TRUE,Journal!$D:$D,"ACHAT",Journal!$E:$E,A16)/SUMIFS(Journal!$K:$K,Journal!$B:$B,TRUE,Journal!$D:$D,"ACHAT",Journal!$E:$E,A16),"")
F17: =IFERROR(SUMIFS(Journal!$K:$K,Journal!$B:$B,TRUE,Journal!$E:$E,A17),0) | G17: =IFERROR(INT(F17/E17),0) | H17: =IFERROR(MOD(F17,E17),0) | I17: =IFERROR(SUMIFS(Journal!$N:$N,Journal!$B:$B,TRUE,Journal!$D:$D,"ACHAT",Journal!$E:$E,A17)/SUMIFS(Journal!$K:$K,Journal!$B:$B,TRUE,Journal!$D:$D,"ACHAT",Journal!$E:$E,A17),"")
F18: =IFERROR(SUMIFS(Journal!$K:$K,Journal!$B:$B,TRUE,Journal!$E:$E,A18),0) | G18: =IFERROR(INT(F18/E18),0) | H18: =IFERROR(MOD(F18,E18),0) | I18: =IFERROR(SUMIFS(Journal!$N:$N,Journal!$B:$B,TRUE,Journal!$D:$D,"ACHAT",Journal!$E:$E,A18)/SUMIFS(Journal!$K:$K,Journal!$B:$B,TRUE,Journal!$D:$D,"ACHAT",Journal!$E:$E,A18),"")
... F206: =IFERROR(SUMIFS(Journal!$K:$K,Journal!$B:$B,TRUE,Journal!$E:$E,A206),0) | G206: =IFERROR(INT(F206/E206),0) | H206: =IFERROR(MOD(F206,E206),0) | I206: =IFERROR(SUMIFS(Journal!$N:$N,Journal!$B:$B,TRUE,Journal!$D:$D,"ACHAT",Journal!$E:$E,A206)/SUMIFS(Journal!$K:$K,Journal!$B:$B,TRUE,Journal!$D:$D,"ACHAT",Journal!$E:$E,A206),"")

Sheet Journal
A1: 📒 JOURNAL — 1 ligne = 1 mouvement. Colonne 'Actif' permet d'annuler ET de rétablir une annulation.
A2: Saisie (vert) : Actif, Date, Type, Produit (PID), Lots, Unités/lot, Unités (saisie), Prix achat lot, Prix vente unitaire, Note. Le reste est calculé.
A3: MID | B3: Actif | C3: Date | D3: Type | E3: PID produit | F3: ID affiché | G3: Nom | H3: Lots (achat) | I3: Unités/lot (achat) | J3: Unités (saisie) | K3: Qty unités (calc) | L3: Prix achat lot (€) | M3: Prix achat unit (€) | N3: Montant achat (€) | O3: Prix vente unit (€) | P3: Montant vente (€) | Q3: Note
A4: M000001 | B4: TRUE | C4: 2025-08-20 | D4: DEPENSE | F4: =IF(E4="","",VLOOKUP(E4,Produits!$A:$J,2,FALSE)) | G4: =IF(E4="","",VLOOKUP(E4,Produits!$A:$J,3,FALSE)) | K4: =IF(B4=FALSE,"",IF(D4="ACHAT",IF(AND(H4<>"",I4<>""),H4*I4,J4),IF(OR(D4="VENTE",D4="PERTE"),-ABS(J4),IF(D4="AJUSTEMENT",J4,"")))) | M4: =IF(OR(L4="",I4=""),"",L4/I4) | N4: =IF(D4<>"ACHAT","",K4*M4) | P4: =IF(D4<>"VENTE","",ABS(K4)*O4) | Q4: Longer Ray5 20w
A5: M000002 | B5: TRUE | C5: 2025-08-20 | D5: DEPENSE | F5: =IF(E5="","",VLOOKUP(E5,Produits!$A:$J,2,FALSE)) | G5: =IF(E5="","",VLOOKUP(E5,Produits!$A:$J,3,FALSE)) | K5: =IF(B5=FALSE,"",IF(D5="ACHAT",IF(AND(H5<>"",I5<>""),H5*I5,J5),IF(OR(D5="VENTE",D5="PERTE"),-ABS(J5),IF(D5="AJUSTEMENT",J5,"")))) | M5: =IF(OR(L5="",I5=""),"",L5/I5) | N5: =IF(D5<>"ACHAT","",K5*M5) | P5: =IF(D5<>"VENTE","",ABS(K5)*O5) | Q5: Pompe à air
A6: M000003 | B6: TRUE | C6: 2025-10-14 | D6: DEPENSE | F6: =IF(E6="","",VLOOKUP(E6,Produits!$A:$J,2,FALSE)) | G6: =IF(E6="","",VLOOKUP(E6,Produits!$A:$J,3,FALSE)) | K6: =IF(B6=FALSE,"",IF(D6="ACHAT",IF(AND(H6<>"",I6<>""),H6*I6,J6),IF(OR(D6="VENTE",D6="PERTE"),-ABS(J6),IF(D6="AJUSTEMENT",J6,"")))) | M6: =IF(OR(L6="",I6=""),"",L6/I6) | N6: =IF(D6<>"ACHAT","",K6*M6) | P6: =IF(D6<>"VENTE","",ABS(K6)*O6) | Q6: Table nid d'abeille
A7: M000004 | B7: TRUE | C7: 2025-09-11 | D7: ACHAT | E7: P69BCEF762C | F7: =IF(E7="","",VLOOKUP(E7,Produits!$A:$J,2,FALSE)) | G7: =IF(E7="","",VLOOKUP(E7,Produits!$A:$J,3,FALSE)) | H7: 0 | I7: 0 | J7: 12 | K7: =IF(B7=FALSE,"",IF(D7="ACHAT",IF(AND(H7<>"",I7<>""),H7*I7,J7),IF(OR(D7="VENTE",D7="PERTE"),-ABS(J7),IF(D7="AJUSTEMENT",J7,"")))) | L7: 13.99 | M7: =IF(OR(L7="",I7=""),"",L7/I7) | N7: =IF(D7<>"ACHAT","",K7*M7) | P7: =IF(D7<>"VENTE","",ABS(K7)*O7)
A8: M000005 | B8: TRUE | C8: 2025-10-29 | D8: ACHAT | E8: P6B0BD97B79 | F8: =IF(E8="","",VLOOKUP(E8,Produits!$A:$J,2,FALSE)) | G8: =IF(E8="","",VLOOKUP(E8,Produits!$A:$J,3,FALSE)) | H8: 0 | I8: 0 | J8: 20 | K8: =IF(B8=FALSE,"",IF(D8="ACHAT",IF(AND(H8<>"",I8<>""),H8*I8,J8),IF(OR(D8="VENTE",D8="PERTE"),-ABS(J8),IF(D8="AJUSTEMENT",J8,"")))) | L8: 28.58 | M8: =IF(OR(L8="",I8=""),"",L8/I8) | N8: =IF(D8<>"ACHAT","",K8*M8) | P8: =IF(D8<>"VENTE","",ABS(K8)*O8)
A9: M000006 | B9: TRUE | C9: 2026-01-11 | D9: ACHAT | E9: P8B70051EAB | F9: =IF(E9="","",VLOOKUP(E9,Produits!$A:$J,2,FALSE)) | G9: =IF(E9="","",VLOOKUP(E9,Produits!$A:$J,3,FALSE)) | H9: 0 | I9: 0 | J9: 16 | K9: =IF(B9=FALSE,"",IF(D9="ACHAT",IF(AND(H9<>"",I9<>""),H9*I9,J9),IF(OR(D9="VENTE",D9="PERTE"),-ABS(J9),IF(D9="AJUSTEMENT",J9,"")))) | L9: 18.98 | M9: =IF(OR(L9="",I9=""),"",L9/I9) | N9: =IF(D9<>"ACHAT","",K9*M9) | P9: =IF(D9<>"VENTE","",ABS(K9)*O9)
A10: M000007 | B10: TRUE | C10: 2026-01-11 | D10: ACHAT | E10: P69BCEF762C | F10: =IF(E10="","",VLOOKUP(E10,Produits!$A:$J,2,FALSE)) | G10: =IF(E10="","",VLOOKUP(E10,Produits!$A:$J,3,FALSE)) | H10: 0 | I10: 0 | J10: 24 | K10: =IF(B10=FALSE,"",IF(D10="ACHAT",IF(AND(H10<>"",I10<>""),H10*I10,J10),IF(OR(D10="VENTE",D10="PERTE"),-ABS(J10),IF(D10="AJUSTEMENT",J10,"")))) | L10: 22.99 | M10: =IF(OR(L10="",I10=""),"",L10/I10) | N10: =IF(D10<>"ACHAT","",K10*M10) | P10: =IF(D10<>"VENTE","",ABS(K10)*O10)
A11: M000008 | B11: TRUE | C11: 2025-11-16 | D11: ACHAT | E11: P69BCEF762C | F11: =IF(E11="","",VLOOKUP(E11,Produits!$A:$J,2,FALSE)) | G11: =IF(E11="","",VLOOKUP(E11,Produits!$A:$J,3,FALSE)) | H11: 0 | I11: 0 | J11: 8 | K11: =IF(B11=FALSE,"",IF(D11="ACHAT",IF(AND(H11<>"",I11<>""),H11*I11,J11),IF(OR(D11="VENTE",D11="PERTE"),-ABS(J11),IF(D11="AJUSTEMENT",J11,"")))) | L11: 8.19 | M11: =IF(OR(L11="",I11=""),"",L11/I11) | N11: =IF(D11<>"ACHAT","",K11*M11) | P11: =IF(D11<>"VENTE","",ABS(K11)*O11)
F12: =IF(E12="","",VLOOKUP(E12,Produits!$A:$J,2,FALSE)) | G12: =IF(E12="","",VLOOKUP(E12,Produits!$A:$J,3,FALSE)) | K12: =IF(B12=FALSE,"",IF(D12="ACHAT",IF(AND(H12<>"",I12<>""),H12*I12,J12),IF(OR(D12="VENTE",D12="PERTE"),-ABS(J12),IF(D12="AJUSTEMENT",J12,"")))) | M12: =IF(OR(L12="",I12=""),"",L12/I12) | N12: =IF(D12<>"ACHAT","",K12*M12) | P12: =IF(D12<>"VENTE","",ABS(K12)*O12)
F13: =IF(E13="","",VLOOKUP(E13,Produits!$A:$J,2,FALSE)) | G13: =IF(E13="","",VLOOKUP(E13,Produits!$A:$J,3,FALSE)) | K13: =IF(B13=FALSE,"",IF(D13="ACHAT",IF(AND(H13<>"",I13<>""),H13*I13,J13),IF(OR(D13="VENTE",D13="PERTE"),-ABS(J13),IF(D13="AJUSTEMENT",J13,"")))) | M13: =IF(OR(L13="",I13=""),"",L13/I13) | N13: =IF(D13<>"ACHAT","",K13*M13) | P13: =IF(D13<>"VENTE","",ABS(K13)*O13)
F14: =IF(E14="","",VLOOKUP(E14,Produits!$A:$J,2,FALSE)) | G14: =IF(E14="","",VLOOKUP(E14,Produits!$A:$J,3,FALSE)) | K14: =IF(B14=FALSE,"",IF(D14="ACHAT",IF(AND(H14<>"",I14<>""),H14*I14,J14),IF(OR(D14="VENTE",D14="PERTE"),-ABS(J14),IF(D14="AJUSTEMENT",J14,"")))) | M14: =IF(OR(L14="",I14=""),"",L14/I14) | N14: =IF(D14<>"ACHAT","",K14*M14) | P14: =IF(D14<>"VENTE","",ABS(K14)*O14)
F15: =IF(E15="","",VLOOKUP(E15,Produits!$A:$J,2,FALSE)) | G15: =IF(E15="","",VLOOKUP(E15,Produits!$A:$J,3,FALSE)) | K15: =IF(B15=FALSE,"",IF(D15="ACHAT",IF(AND(H15<>"",I15<>""),H15*I15,J15),IF(OR(D15="VENTE",D15="PERTE"),-ABS(J15),IF(D15="AJUSTEMENT",J15,"")))) | M15: =IF(OR(L15="",I15=""),"",L15/I15) | N15: =IF(D15<>"ACHAT","",K15*M15) | P15: =IF(D15<>"VENTE","",ABS(K15)*O15)
F16: =IF(E16="","",VLOOKUP(E16,Produits!$A:$J,2,FALSE)) | G16: =IF(E16="","",VLOOKUP(E16,Produits!$A:$J,3,FALSE)) | K16: =IF(B16=FALSE,"",IF(D16="ACHAT",IF(AND(H16<>"",I16<>""),H16*I16,J16),IF(OR(D16="VENTE",D16="PERTE"),-ABS(J16),IF(D16="AJUSTEMENT",J16,"")))) | M16: =IF(OR(L16="",I16=""),"",L16/I16) | N16: =IF(D16<>"ACHAT","",K16*M16) | P16: =IF(D16<>"VENTE","",ABS(K16)*O16)
F17: =IF(E17="","",VLOOKUP(E17,Produits!$A:$J,2,FALSE)) | G17: =IF(E17="","",VLOOKUP(E17,Produits!$A:$J,3,FALSE)) | K17: =IF(B17=FALSE,"",IF(D17="ACHAT",IF(AND(H17<>"",I17<>""),H17*I17,J17),IF(OR(D17="VENTE",D17="PERTE"),-ABS(J17),IF(D17="AJUSTEMENT",J17,"")))) | M17: =IF(OR(L17="",I17=""),"",L17/I17) | N17: =IF(D17<>"ACHAT","",K17*M17) | P17: =IF(D17<>"VENTE","",ABS(K17)*O17)
F18: =IF(E18="","",VLOOKUP(E18,Produits!$A:$J,2,FALSE)) | G18: =IF(E18="","",VLOOKUP(E18,Produits!$A:$J,3,FALSE)) | K18: =IF(B18=FALSE,"",IF(D18="ACHAT",IF(AND(H18<>"",I18<>""),H18*I18,J18),IF(OR(D18="VENTE",D18="PERTE"),-ABS(J18),IF(D18="AJUSTEMENT",J18,"")))) | M18: =IF(OR(L18="",I18=""),"",L18/I18) | N18: =IF(D18<>"ACHAT","",K18*M18) | P18: =IF(D18<>"VENTE","",ABS(K18)*O18)
F19: =IF(E19="","",VLOOKUP(E19,Produits!$A:$J,2,FALSE)) | G19: =IF(E19="","",VLOOKUP(E19,Produits!$A:$J,3,FALSE)) | K19: =IF(B19=FALSE,"",IF(D19="ACHAT",IF(AND(H19<>"",I19<>""),H19*I19,J19),IF(OR(D19="VENTE",D19="PERTE"),-ABS(J19),IF(D19="AJUSTEMENT",J19,"")))) | M19: =IF(OR(L19="",I19=""),"",L19/I19) | N19: =IF(D19<>"ACHAT","",K19*M19) | P19: =IF(D19<>"VENTE","",ABS(K19)*O19)
F20: =IF(E20="","",VLOOKUP(E20,Produits!$A:$J,2,FALSE)) | G20: =IF(E20="","",VLOOKUP(E20,Produits!$A:$J,3,FALSE)) | K20: =IF(B20=FALSE,"",IF(D20="ACHAT",IF(AND(H20<>"",I20<>""),H20*I20,J20),IF(OR(D20="VENTE",D20="PERTE"),-ABS(J20),IF(D20="AJUSTEMENT",J20,"")))) | M20: =IF(OR(L20="",I20=""),"",L20/I20) | N20: =IF(D20<>"ACHAT","",K20*M20) | P20: =IF(D20<>"VENTE","",ABS(K20)*O20)
F21: =IF(E21="","",VLOOKUP(E21,Produits!$A:$J,2,FALSE)) | G21: =IF(E21="","",VLOOKUP(E21,Produits!$A:$J,3,FALSE)) | K21: =IF(B21=FALSE,"",IF(D21="ACHAT",IF(AND(H21<>"",I21<>""),H21*I21,J21),IF(OR(D21="VENTE",D21="PERTE"),-ABS(J21),IF(D21="AJUSTEMENT",J21,"")))) | M21: =IF(OR(L21="",I21=""),"",L21/I21) | N21: =IF(D21<>"ACHAT","",K21*M21) | P21: =IF(D21<>"VENTE","",ABS(K21)*O21)
F22: =IF(E22="","",VLOOKUP(E22,Produits!$A:$J,2,FALSE)) | G22: =IF(E22="","",VLOOKUP(E22,Produits!$A:$J,3,FALSE)) | K22: =IF(B22=FALSE,"",IF(D22="ACHAT",IF(AND(H22<>"",I22<>""),H22*I22,J22),IF(OR(D22="VENTE",D22="PERTE"),-ABS(J22),IF(D22="AJUSTEMENT",J22,"")))) | M22: =IF(OR(L22="",I22=""),"",L22/I22) | N22: =IF(D22<>"ACHAT","",K22*M22) | P22: =IF(D22<>"VENTE","",ABS(K22)*O22)
F23: =IF(E23="","",VLOOKUP(E23,Produits!$A:$J,2,FALSE)) | G23: =IF(E23="","",VLOOKUP(E23,Produits!$A:$J,3,FALSE)) | K23: =IF(B23=FALSE,"",IF(D23="ACHAT",IF(AND(H23<>"",I23<>""),H23*I23,J23),IF(OR(D23="VENTE",D23="PERTE"),-ABS(J23),IF(D23="AJUSTEMENT",J23,"")))) | M23: =IF(OR(L23="",I23=""),"",L23/I23) | N23: =IF(D23<>"ACHAT","",K23*M23) | P23: =IF(D23<>"VENTE","",ABS(K23)*O23)
... F211: =IF(E211="","",VLOOKUP(E211,Produits!$A:$J,2,FALSE)) | G211: =IF(E211="","",VLOOKUP(E211,Produits!$A:$J,3,FALSE)) | K211: =IF(B211=FALSE,"",IF(D211="ACHAT",IF(AND(H211<>"",I211<>""),H211*I211,J211),IF(OR(D211="VENTE",D211="PERTE"),-ABS(J211),IF(D211="AJUSTEMENT",J211,"")))) | M211: =IF(OR(L211="",I211=""),"",L211/I211) | N211: =IF(D211<>"ACHAT","",K211*M211) | P211: =IF(D211<>"VENTE","",ABS(K211)*O211)

Sheet README
A1: 80085 — Modifs demandées (ID modifiable + annulation réversible + journal éditable)
A3: 1) Chaque produit a un PID interne (colonne cachée dans Produits). Tu peux changer 'ID produit' sans casser le Journal.
A4: 2) Le Journal référence le PID. L'ID affiché et le nom se recalculent automatiquement.
A5: 3) Annuler / rétablir : coche/décoche la colonne 'Actif' dans le Journal. Les calculs ne prennent en compte que Actif=TRUE.
A6: 4) Tu peux modifier après coup Lots / Unités/lot / Unités / Prix achat lot / Prix vente unitaire : tout se recalcule.
A8: Tips mobile : filtre sur Type, et garde les colonnes A-D + F-G + H-J + L-O visibles.
